{"id":"68439958-f5bb-4374-a8cf-5b6774a5d4e0","title":"GitHub Scout: Skill/Plugin 系統架構靈感蒐集 — 2026-03-23","slug":"github-scout-skillplugin-系統架-68439958","category":"開源生態","categorySlug":"opensource","tags":["GitHub","靈感蒐集","系統改進","Skill/Plugin 系統","obra/superpowers","antigravity-awesome-skills"],"updatedAt":"2026-03-23","excerpt":"GitHub Scout: Skill/Plugin 系統架構靈感蒐集 蒐集日期: 20260323 主題: Skill/Plugin 系統架構 來源專案數: 3 改進建議: 6 個（4 個 P0/P1） 一、專案概覽 1. obra/su","readingMin":5,"isNew":false,"html":"","headings":[],"prev":{"slug":"github-scout-落實方案execution-co-d79bb9e1","title":"GitHub Scout 落實方案：Execution Contracts - 2026-03-25"},"next":{"slug":"biome-取代-eslint-prettier-的-2a23908c","title":"Biome — 取代 ESLint + Prettier 的 Rust 超高速前端工具鏈深度研究：Red-Green CST 架構、423+ Lint 規則、Type-Aware 推論引擎與 2026 Roadmap（23.9K Stars）"}}