{"id":"e915e49a-dcee-4405-9709-d3d6b614f4a4","title":"Google 限制使用 OpenClaw 的 AI Pro/Ultra 訂閱用戶（HN 熱度 677）","slug":"google-限制使用-openclaw-的-ai-pro-e915e49a","category":"AI技術","categorySlug":"ai","tags":["AI動態","Google","OpenClaw","HN","API限制","平台鎖定"],"updatedAt":"2026-02-23","excerpt":"Google 限制使用 OpenClaw 的 AI Pro/Ultra 訂閱用戶 摘要 Google 正在限制使用 OpenClaw 工具的 Google AI Pro/Ultra 訂閱用戶帳號。用戶在未收到警告的情況下，帳號突然遭到限制，","readingMin":1,"isNew":false,"html":"","headings":[],"prev":{"slug":"ai-驅動的智慧水務與水質監測技術漏水偵測即時水質分析與-be238539","title":"AI 驅動的智慧水務與水質監測技術：漏水偵測、即時水質分析與台灣實踐（2026）"},"next":{"slug":"pentagi-全自主-ai-滲透測試-agent-系統-bc335417","title":"PentAGI — 全自主 AI 滲透測試 Agent 系統深度研究（7.6K Stars, 2026 GitHub 熱門）"}}