{"id":"cba377cc-3eb0-44ad-9cc0-85dc1f1a3e82","title":"HTML5 遊戲存檔系統設計完整指南：LocalStorage、IndexedDB、狀態序列化與雲端同步（2026）","slug":"html5-localstorage-indexeddb-2-cba377cc","category":"遊戲開發","categorySlug":"game","tags":["技術研究","遊戲存檔系統","LocalStorage","IndexedDB","狀態序列化","雲端同步","HTML5遊戲","遊戲開發","設計模式","效能優化","daily-digest"],"updatedAt":"2026-02-19","excerpt":"HTML5 遊戲存檔系統設計完整指南（2026） 技術概述 遊戲存檔系統是 HTML5 遊戲開發中常被忽視卻至關重要的基礎設施。良好的存檔系統需要兼顧持久性、效能、容錯性與擴展性。Web 平台提供了多種客戶端儲存方案（LocalStorag","readingMin":11,"isNew":false,"html":"<h1 id=\"html5-遊戲存檔系統設計完整指南-2026\">HTML5 遊戲存檔系統設計完整指南（2026）</h1>\n<h2 id=\"技術概述\">技術概述</h2>\n<p>遊戲存檔系統是 HTML5 遊戲開發中常被忽視卻至關重要的基礎設施。良好的存檔系統需要兼顧持久性、效能、容錯性與擴展性。Web 平台提供了多種客戶端儲存方案（LocalStorage、IndexedDB、OPFS），各有優劣。本指南系統整理存檔架構設計模式、狀態序列化策略、儲存引擎選型與雲端同步方案，特別著重 HTML5 Canvas 遊戲的實際應用。</p>\n<hr>\n<h2 id=\"一-儲存引擎比較與選型\">一、儲存引擎比較與選型</h2>\n<h3 id=\"1-1-三大客戶端儲存方案\">1.1 三大客戶端儲存方案</h3>\n<table>\n<tr><th>特性</th><th>LocalStorage</th><th>IndexedDB</th><th>OPFS (Origin Private File System)</th></tr>\n<tr><td><strong>API 風格</strong></td><td>同步（阻塞）</td><td>非同步（Promise/事件）</td><td>非同步（Promise）</td></tr>\n<tr><td><strong>容量上限</strong></td><td>5 MiB / origin</td><td>Chrome: 60% 磁碟; Firefox: 10% 磁碟 (max 10 GiB)</td><td>同 IndexedDB</td></tr>\n<tr><td><strong>資料型別</strong></td><td>僅字串（UTF-16）</td><td>結構化物件、Blob、ArrayBuffer</td><td>檔案（二進位）</td></tr>\n<tr><td><strong>索引查詢</strong></td><td>無（僅 key-value）</td><td>支援多重索引、範圍查詢、游標遍歷</td><td>無（檔案系統語義）</td></tr>\n<tr><td><strong>交易支援</strong></td><td>無</td><td>完整 ACID 交易（readonly / readwrite）</td><td>無</td></tr>\n<tr><td><strong>適用場景</strong></td><td>簡單設定、高分紀錄、小型存檔 (&lt;100KB)</td><td>複雜存檔、多存檔槽、大量結構化資料</td><td>大型二進位資源、離線快取</td></tr>\n<tr><td><strong>瀏覽器支援</strong></td><td>全部</td><td>全部（IE10+）</td><td>Chrome 86+, Firefox 111+, Safari 15.2+</td></tr>\n</table>\n<h3 id=\"1-2-選型決策樹\">1.2 選型決策樹</h3>\n<pre><code class=\"language-plaintext\">存檔資料 &lt; 100KB 且結構簡單？\n  ├─ 是 → LocalStorage（最簡方案）\n  └─ 否 → 需要索引查詢或多存檔槽？\n        ├─ 是 → IndexedDB（推薦方案）\n        └─ 否 → 大型二進位資源？\n              ├─ 是 → OPFS\n              └─ 否 → IndexedDB（通用方案）</code></pre>\n<h3 id=\"1-3-混合策略-推薦\">1.3 混合策略（推薦）</h3>\n<p>實務上最佳方案是<strong>分層儲存</strong>：</p>\n<ul>\n<li><strong>LocalStorage</strong>：遊戲設定（音量、語言、控制鍵位）、最後使用的存檔槽 ID</li>\n<li><strong>IndexedDB</strong>：完整遊戲狀態（角色、關卡、物品）、存檔中繼資料</li>\n<li><strong>伺服器端</strong>：雲端備份、跨裝置同步、排行榜</li>\n</ul>\n<hr>\n<h2 id=\"二-遊戲狀態序列化設計\">二、遊戲狀態序列化設計</h2>\n<h3 id=\"2-1-存檔資料結構設計\">2.1 存檔資料結構設計</h3>\n<p>良好的存檔結構應包含：</p>\n<pre><code class=\"language-javascript\">const saveData = {\n  // 中繼資料（meta）\n  meta: {\n    version: '1.2.0',        // 存檔格式版本（遷移用）\n    saveSlot: 1,             // 存檔槽編號\n    timestamp: Date.now(),   // 存檔時間戳\n    playTime: 3600,          // 累計遊玩秒數\n    checksum: 'sha256-hash'  // 資料完整性校驗\n  },\n  // 玩家狀態\n  player: {\n    name: 'Alice',\n    level: 5,\n    hp: 80,\n    maxHp: 100,\n    position: { x: 120, y: 450 },\n    stats: { str: 12, dex: 15, int: 10 }\n  },\n  // 遊戲進度\n  progress: {\n    currentStage: 'forest-3',\n    completedStages: ['tutorial', 'forest-1', 'forest-2'],\n    score: 25000,\n    achievements: ['first-kill', 'no-damage-clear']\n  },\n  // 物品欄\n  inventory: [\n    { id: 'sword-001', type: 'weapon', quantity: 1 },\n    { id: 'potion-hp', type: 'consumable', quantity: 5 }\n  ],\n  // 遊戲世界狀態\n  world: {\n    npcStates: { merchant: 'friendly', guard: 'neutral' },\n    doorStates: { 'door-A': 'unlocked', 'door-B': 'locked' },\n    collectibles: ['coin-1', 'coin-3'] // 已收集的項目\n  }\n};</code></pre>\n<h3 id=\"2-2-序列化與反序列化\">2.2 序列化與反序列化</h3>\n<p>#### LocalStorage 方案（簡單遊戲）</p>\n<pre><code class=\"language-javascript\">class SimpleSaveManager {\n  static SAVE_KEY = 'game-save';\n\n  static save(gameState) {\n    try {\n      const data = JSON.stringify(gameState);\n      localStorage.setItem(this.SAVE_KEY, data);\n      return true;\n    } catch (e) {\n      if (e.name === 'QuotaExceededError') {\n        console.warn('儲存空間已滿，嘗試清理舊資料');\n        this.cleanupOldData();\n        return false;\n      }\n      throw e;\n    }\n  }\n\n  static load() {\n    const raw = localStorage.getItem(this.SAVE_KEY);\n    if (!raw) return null;\n    try {\n      return JSON.parse(raw);\n    } catch (e) {\n      console.error('存檔損壞，重置為預設值');\n      localStorage.removeItem(this.SAVE_KEY);\n      return null;\n    }\n  }\n\n  static cleanupOldData() {\n    // 移除非關鍵資料\n    const keysToKeep = [this.SAVE_KEY, 'game-settings'];\n    for (let i = localStorage.length - 1; i &gt;= 0; i--) {\n      const key = localStorage.key(i);\n      if (!keysToKeep.includes(key)) {\n        localStorage.removeItem(key);\n      }\n    }\n  }\n}</code></pre>\n<p>#### IndexedDB 方案（複雜遊戲）</p>\n<pre><code class=\"language-javascript\">class IndexedDBSaveManager {\n  constructor(dbName = 'GameSaves', version = 1) {\n    this.dbName = dbName;\n    this.version = version;\n    this.db = null;\n  }\n\n  async init() {\n    return new Promise((resolve, reject) =&gt; {\n      const request = indexedDB.open(this.dbName, this.version);\n\n      request.onupgradeneeded = (event) =&gt; {\n        const db = event.target.result;\n        if (!db.objectStoreNames.contains('saves')) {\n          const store = db.createObjectStore('saves', { keyPath: 'slotId' });\n          store.createIndex('timestamp', 'meta.timestamp', { unique: false });\n          store.createIndex('playerName', 'player.name', { unique: false });\n        }\n        if (!db.objectStoreNames.contains('settings')) {\n          db.createObjectStore('settings', { keyPath: 'key' });\n        }\n      };\n\n      request.onsuccess = (event) =&gt; {\n        this.db = event.target.result;\n        // 監聽其他分頁的版本變更\n        this.db.onversionchange = () =&gt; {\n          this.db.close();\n          alert('遊戲資料庫已更新，請重新整理頁面');\n        };\n        resolve(this.db);\n      };\n\n      request.onerror = (event) =&gt; reject(event.target.error);\n    });\n  }\n\n  async save(slotId, gameState) {\n    const data = { slotId, ...gameState, meta: { ...gameState.meta, timestamp: Date.now() } };\n    return new Promise((resolve, reject) =&gt; {\n      const tx = this.db.transaction(['saves'], 'readwrite');\n      tx.objectStore('saves').put(data);\n      tx.oncomplete = () =&gt; resolve(true);\n      tx.onerror = (event) =&gt; reject(event.target.error);\n    });\n  }\n\n  async load(slotId) {\n    return new Promise((resolve, reject) =&gt; {\n      const tx = this.db.transaction(['saves'], 'readonly');\n      const request = tx.objectStore('saves').get(slotId);\n      request.onsuccess = () =&gt; resolve(request.result || null);\n      request.onerror = (event) =&gt; reject(event.target.error);\n    });\n  }\n\n  async listSaves() {\n    return new Promise((resolve, reject) =&gt; {\n      const tx = this.db.transaction(['saves'], 'readonly');\n      const request = tx.objectStore('saves').getAll();\n      request.onsuccess = () =&gt; {\n        const saves = request.result.map(s =&gt; ({\n          slotId: s.slotId,\n          playerName: s.player?.name,\n          level: s.player?.level,\n          timestamp: s.meta?.timestamp,\n          playTime: s.meta?.playTime\n        }));\n        resolve(saves.sort((a, b) =&gt; b.timestamp - a.timestamp));\n      };\n      request.onerror = (event) =&gt; reject(event.target.error);\n    });\n  }\n\n  async deleteSave(slotId) {\n    return new Promise((resolve, reject) =&gt; {\n      const tx = this.db.transaction(['saves'], 'readwrite');\n      tx.objectStore('saves').delete(slotId);\n      tx.oncomplete = () =&gt; resolve(true);\n      tx.onerror = (event) =&gt; reject(event.target.error);\n    });\n  }\n}</code></pre>\n<hr>\n<h2 id=\"三-自動存檔策略\">三、自動存檔策略</h2>\n<h3 id=\"3-1-觸發時機設計\">3.1 觸發時機設計</h3>\n<table>\n<tr><th>觸發點</th><th>適用場景</th><th>注意事項</th></tr>\n<tr><td><strong>定時自動存檔</strong></td><td>所有遊戲</td><td>每 30-60 秒，避免在戰鬥/過場動畫中觸發</td></tr>\n<tr><td><strong>檢查點存檔</strong></td><td>關卡制遊戲</td><td>過關、到達安全區時自動存檔</td></tr>\n<tr><td><strong>事件驅動存檔</strong></td><td>RPG/策略遊戲</td><td>重要決策後、獲得道具後、對話結束後</td></tr>\n<tr><td><strong>頁面可見性變更</strong></td><td>行動裝置遊戲</td><td><code>visibilitychange</code> 事件，切換應用程式時存檔</td></tr>\n<tr><td><strong>手動存檔</strong></td><td>所有遊戲</td><td>玩家主動按存檔按鈕</td></tr>\n</table>\n<h3 id=\"3-2-自動存檔實作\">3.2 自動存檔實作</h3>\n<pre><code class=\"language-javascript\">class AutoSaveSystem {\n  constructor(saveManager, intervalMs = 30000) {\n    this.saveManager = saveManager;\n    this.intervalMs = intervalMs;\n    this.timerId = null;\n    this.isDirty = false;  // 狀態是否有變更\n    this.isSaving = false; // 防止並發存檔\n  }\n\n  start(getStateFn) {\n    // 定時存檔\n    this.timerId = setInterval(() =&gt; {\n      if (this.isDirty &amp;&amp; !this.isSaving) {\n        this.performSave(getStateFn());\n      }\n    }, this.intervalMs);\n\n    // 頁面隱藏時存檔（行動裝置切換 App）\n    document.addEventListener('visibilitychange', () =&gt; {\n      if (document.hidden &amp;&amp; this.isDirty) {\n        this.performSave(getStateFn());\n      }\n    });\n\n    // 頁面關閉前存檔（不保證成功）\n    window.addEventListener('beforeunload', () =&gt; {\n      if (this.isDirty) {\n        // 使用 sendBeacon 或同步 localStorage 作為最後手段\n        const data = JSON.stringify(getStateFn());\n        localStorage.setItem('emergency-save', data);\n      }\n    });\n  }\n\n  async performSave(state) {\n    this.isSaving = true;\n    try {\n      await this.saveManager.save('auto', state);\n      this.isDirty = false;\n      console.log('自動存檔完成');\n    } catch (e) {\n      console.error('自動存檔失敗:', e);\n    } finally {\n      this.isSaving = false;\n    }\n  }\n\n  markDirty() {\n    this.isDirty = true;\n  }\n\n  stop() {\n    if (this.timerId) {\n      clearInterval(this.timerId);\n      this.timerId = null;\n    }\n  }\n}</code></pre>\n<hr>\n<h2 id=\"四-存檔版本遷移\">四、存檔版本遷移</h2>\n<p>遊戲更新後存檔格式可能改變，需要遷移機制：</p>\n<pre><code class=\"language-javascript\">class SaveMigrator {\n  static CURRENT_VERSION = '1.2.0';\n\n  // 遷移函數註冊表\n  static migrations = {\n    '1.0.0_to_1.1.0': (data) =&gt; {\n      // v1.1.0 新增 stats 欄位\n      data.player.stats = data.player.stats || { str: 10, dex: 10, int: 10 };\n      data.meta.version = '1.1.0';\n      return data;\n    },\n    '1.1.0_to_1.2.0': (data) =&gt; {\n      // v1.2.0 重構 inventory 格式\n      if (Array.isArray(data.inventory)) {\n        data.inventory = data.inventory.map(item =&gt; ({\n          ...item,\n          durability: item.durability ?? 100\n        }));\n      }\n      data.meta.version = '1.2.0';\n      return data;\n    }\n  };\n\n  static MIGRATION_ORDER = ['1.0.0', '1.1.0', '1.2.0'];\n\n  static migrate(saveData) {\n    let currentVersion = saveData.meta?.version || '1.0.0';\n\n    if (currentVersion === this.CURRENT_VERSION) {\n      return saveData; // 已是最新版本\n    }\n\n    const startIdx = this.MIGRATION_ORDER.indexOf(currentVersion);\n    if (startIdx === -1) {\n      console.error('未知的存檔版本:', currentVersion);\n      return null; // 無法遷移\n    }\n\n    for (let i = startIdx; i &lt; this.MIGRATION_ORDER.length - 1; i++) {\n      const from = this.MIGRATION_ORDER[i];\n      const to = this.MIGRATION_ORDER[i + 1];\n      const migrationKey = `${from}_to_${to}`;\n\n      if (this.migrations[migrationKey]) {\n        console.log(`遷移存檔: ${from} -&gt; ${to}`);\n        saveData = this.migrations[migrationKey](saveData);\n      }\n    }\n\n    return saveData;\n  }\n}</code></pre>\n<hr>\n<h2 id=\"五-資料完整性與防竄改\">五、資料完整性與防竄改</h2>\n<h3 id=\"5-1-校驗和驗證\">5.1 校驗和驗證</h3>\n<pre><code class=\"language-javascript\">class SaveIntegrity {\n  // 簡易校驗和（非加密級，防意外損壞）\n  static generateChecksum(data) {\n    const str = JSON.stringify(data);\n    let hash = 0;\n    for (let i = 0; i &lt; str.length; i++) {\n      const char = str.charCodeAt(i);\n      hash = ((hash &lt;&lt; 5) - hash) + char;\n      hash = hash &amp; hash; // 轉為 32 位元整數\n    }\n    return hash.toString(16);\n  }\n\n  // Web Crypto API 校驗和（更安全）\n  static async generateSecureChecksum(data) {\n    const str = JSON.stringify(data);\n    const encoder = new TextEncoder();\n    const buffer = encoder.encode(str);\n    const hashBuffer = await crypto.subtle.digest('SHA-256', buffer);\n    const hashArray = Array.from(new Uint8Array(hashBuffer));\n    return hashArray.map(b =&gt; b.toString(16).padStart(2, '0')).join('');\n  }\n\n  static validateSave(saveData) {\n    if (!saveData || !saveData.meta) return false;\n    if (!saveData.meta.version) return false;\n    if (!saveData.meta.timestamp) return false;\n    if (saveData.meta.timestamp &gt; Date.now()) return false; // 未來時間戳\n    // 校驗和驗證\n    const stored = saveData.meta.checksum;\n    const dataCopy = { ...saveData, meta: { ...saveData.meta, checksum: undefined } };\n    const computed = this.generateChecksum(dataCopy);\n    return stored === computed;\n  }\n}</code></pre>\n<h3 id=\"5-2-備份與恢復\">5.2 備份與恢復</h3>\n<pre><code class=\"language-javascript\">class SaveBackupManager {\n  static MAX_BACKUPS = 3;\n\n  // 存檔前自動建立備份\n  static async createBackup(saveManager, slotId) {\n    const current = await saveManager.load(slotId);\n    if (current) {\n      const backupId = `${slotId}-backup-${Date.now()}`;\n      await saveManager.save(backupId, current);\n      // 清理舊備份（保留最近 3 個）\n      await this.pruneBackups(saveManager, slotId);\n    }\n  }\n\n  static async pruneBackups(saveManager, slotId) {\n    const saves = await saveManager.listSaves();\n    const backups = saves\n      .filter(s =&gt; s.slotId.startsWith(`${slotId}-backup-`))\n      .sort((a, b) =&gt; b.timestamp - a.timestamp);\n\n    for (let i = this.MAX_BACKUPS; i &lt; backups.length; i++) {\n      await saveManager.deleteSave(backups[i].slotId);\n    }\n  }\n}</code></pre>\n<hr>\n<h2 id=\"六-雲端同步設計\">六、雲端同步設計</h2>\n<h3 id=\"6-1-同步架構\">6.1 同步架構</h3>\n<pre><code class=\"language-plaintext\">[本地存檔] &lt;---&gt; [同步引擎] &lt;---&gt; [雲端 API]\n    |                |                  |\n  IndexedDB    衝突解決策略      REST/WebSocket\n    |                |                  |\n  自動存檔      版本向量         伺服器端存檔</code></pre>\n<h3 id=\"6-2-衝突解決策略\">6.2 衝突解決策略</h3>\n<table>\n<tr><th>策略</th><th>說明</th><th>適用場景</th></tr>\n<tr><td><strong>Last-Write-Wins</strong></td><td>以最新時間戳為準</td><td>單人遊戲、簡單進度</td></tr>\n<tr><td><strong>Server-Wins</strong></td><td>永遠以伺服器版本為準</td><td>防作弊優先的遊戲</td></tr>\n<tr><td><strong>Client-Wins</strong></td><td>永遠以本地版本為準</td><td>離線優先的遊戲</td></tr>\n<tr><td><strong>合併策略</strong></td><td>欄位級合併（取各欄位最大值）</td><td>RPG（分數取高、道具取聯集）</td></tr>\n<tr><td><strong>玩家選擇</strong></td><td>顯示兩個版本讓玩家選</td><td>複雜的劇情分支遊戲</td></tr>\n</table>\n<h3 id=\"6-3-離線優先同步模式\">6.3 離線優先同步模式</h3>\n<pre><code class=\"language-javascript\">class CloudSyncManager {\n  constructor(saveManager, apiEndpoint) {\n    this.saveManager = saveManager;\n    this.apiEndpoint = apiEndpoint;\n    this.syncQueue = [];  // 待同步操作佇列\n  }\n\n  async sync(slotId) {\n    if (!navigator.onLine) {\n      this.syncQueue.push({ action: 'sync', slotId, timestamp: Date.now() });\n      return { status: 'queued' };\n    }\n\n    const local = await this.saveManager.load(slotId);\n    const remote = await this.fetchRemoteSave(slotId);\n\n    if (!remote) {\n      // 伺服器無存檔，上傳本地\n      await this.uploadSave(slotId, local);\n      return { status: 'uploaded' };\n    }\n\n    if (!local) {\n      // 本地無存檔，下載雲端\n      await this.saveManager.save(slotId, remote);\n      return { status: 'downloaded' };\n    }\n\n    // 衝突解決：比較時間戳\n    if (local.meta.timestamp &gt; remote.meta.timestamp) {\n      await this.uploadSave(slotId, local);\n      return { status: 'uploaded' };\n    } else if (remote.meta.timestamp &gt; local.meta.timestamp) {\n      await this.saveManager.save(slotId, remote);\n      return { status: 'downloaded' };\n    }\n\n    return { status: 'in-sync' };\n  }\n\n  // 網路恢復時處理佇列\n  async processSyncQueue() {\n    while (this.syncQueue.length &gt; 0 &amp;&amp; navigator.onLine) {\n      const task = this.syncQueue.shift();\n      await this.sync(task.slotId);\n    }\n  }\n}\n\n// 監聽網路恢復事件\nwindow.addEventListener('online', () =&gt; {\n  cloudSync.processSyncQueue();\n});</code></pre>\n<hr>\n<h2 id=\"七-效能最佳化\">七、效能最佳化</h2>\n<h3 id=\"7-1-差分存檔-delta-save\">7.1 差分存檔（Delta Save）</h3>\n<p>只儲存與上次存檔不同的部分，減少 I/O：</p>\n<pre><code class=\"language-javascript\">function createDelta(prev, current) {\n  const delta = {};\n  for (const key of Object.keys(current)) {\n    if (JSON.stringify(prev[key]) !== JSON.stringify(current[key])) {\n      delta[key] = current[key];\n    }\n  }\n  return delta;\n}</code></pre>\n<h3 id=\"7-2-壓縮存檔\">7.2 壓縮存檔</h3>\n<p>使用 Compression Streams API（Chrome 80+）：</p>\n<pre><code class=\"language-javascript\">async function compressSaveData(data) {\n  const json = JSON.stringify(data);\n  const blob = new Blob([json]);\n  const cs = new CompressionStream('gzip');\n  const compressedStream = blob.stream().pipeThrough(cs);\n  return new Response(compressedStream).blob();\n}\n\nasync function decompressSaveData(compressedBlob) {\n  const ds = new DecompressionStream('gzip');\n  const decompressedStream = compressedBlob.stream().pipeThrough(ds);\n  const text = await new Response(decompressedStream).text();\n  return JSON.parse(text);\n}</code></pre>\n<h3 id=\"7-3-避免遊戲迴圈中的同步-i-o\">7.3 避免遊戲迴圈中的同步 I/O</h3>\n<pre><code class=\"language-javascript\">// 錯誤：在遊戲迴圈中直接存檔\nfunction gameLoop() {\n  update();\n  render();\n  localStorage.setItem('save', JSON.stringify(state)); // 每幀阻塞！\n  requestAnimationFrame(gameLoop);\n}\n\n// 正確：標記為 dirty，定時非同步存檔\nlet isDirty = false;\nfunction gameLoop() {\n  update();\n  if (stateChanged) isDirty = true;\n  render();\n  requestAnimationFrame(gameLoop);\n}\n// 自動存檔系統在背景處理 isDirty 標記</code></pre>\n<hr>\n<h2 id=\"八-儲存配額與容錯\">八、儲存配額與容錯</h2>\n<h3 id=\"8-1-配額管理\">8.1 配額管理</h3>\n<pre><code class=\"language-javascript\">async function checkStorageQuota() {\n  if (navigator.storage &amp;&amp; navigator.storage.estimate) {\n    const { usage, quota } = await navigator.storage.estimate();\n    const percentUsed = ((usage / quota) * 100).toFixed(2);\n    console.log(`已用 ${percentUsed}%（${(usage/1024/1024).toFixed(1)} MB / ${(quota/1024/1024).toFixed(0)} MB）`);\n    return { usage, quota, percentUsed };\n  }\n  return null;\n}\n\n// 申請持久化儲存（防止瀏覽器自動清理）\nasync function requestPersistentStorage() {\n  if (navigator.storage &amp;&amp; navigator.storage.persist) {\n    const isPersistent = await navigator.storage.persist();\n    console.log(`持久化儲存: ${isPersistent ? '已啟用' : '被拒絕'}`);\n    return isPersistent;\n  }\n  return false;\n}</code></pre>\n<h3 id=\"8-2-驅逐策略與防護\">8.2 驅逐策略與防護</h3>\n<p>瀏覽器在儲存壓力下會自動驅逐 best-effort 模式的資料（LRU 策略）。防護措施：</p>\n<ol>\n<li><strong>申請持久化儲存</strong>：<code>navigator.storage.persist()</code> 防止自動驅逐</li>\n<li><strong>定期備份</strong>：在 IndexedDB 和 LocalStorage 雙寫關鍵資料</li>\n<li><strong>匯出功能</strong>：提供手動匯出 JSON 存檔的功能</li>\n<li><strong>雲端同步</strong>：作為最後防線的備份</li>\n</ol>\n<hr>\n<h2 id=\"九-存檔槽管理-ui-設計\">九、存檔槽管理 UI 設計</h2>\n<h3 id=\"9-1-存檔槽資訊顯示\">9.1 存檔槽資訊顯示</h3>\n<p>每個存檔槽應顯示以下資訊：</p>\n<ul>\n<li>玩家名稱 / 角色等級</li>\n<li>當前關卡 / 遊戲進度百分比</li>\n<li>遊玩時間</li>\n<li>最後存檔時間（相對時間：「2 小時前」）</li>\n<li>存檔縮圖（可選，用 Canvas.toDataURL() 截圖）</li>\n</ul>\n<h3 id=\"9-2-操作流程\">9.2 操作流程</h3>\n<pre><code class=\"language-plaintext\">[存檔選單]\n  ├─ 槽位 1: Alice Lv.5 - 森林第三章 (2h前) [載入] [刪除]\n  ├─ 槽位 2: Bob Lv.12 - 火山要塞 (昨天)   [載入] [刪除]\n  ├─ 槽位 3: (空槽位)                        [新遊戲]\n  ├─ 自動存檔: Alice Lv.5 - 森林第三章 (5分前) [載入]\n  └─ [匯入存檔] [匯出存檔] [雲端同步]</code></pre>\n<hr>\n<h2 id=\"十-應用到-daily-digest-prompt-專案遊戲\">十、應用到 daily-digest-prompt 專案遊戲</h2>\n<h3 id=\"直接適用的模式\">直接適用的模式</h3>\n<table>\n<tr><th>遊戲</th><th>推薦方案</th><th>存檔內容</th></tr>\n<tr><td>輪迴塔 (Roguelike)</td><td>LocalStorage（高分）+ IndexedDB（進度/成就）</td><td>最高分、最高層、解鎖的六道場景、禪字收集</td></tr>\n<tr><td>Pong / Breakout</td><td>LocalStorage</td><td>高分紀錄、難度設定</td></tr>\n<tr><td>念珠冥想</td><td>LocalStorage</td><td>冥想次數統計、連續天數</td></tr>\n<tr><td>六根淨化</td><td>IndexedDB</td><td>關卡進度、淨化紀錄</td></tr>\n</table>\n<h3 id=\"統一存檔介面\">統一存檔介面</h3>\n<p>建議所有遊戲共用一個 <code>SaveManager</code> 介面，內部依遊戲複雜度自動選擇 LocalStorage 或 IndexedDB，確保 API 一致性。</p>\n<hr>\n<h2 id=\"參考來源\">參考來源</h2>\n<ul>\n<li>MDN Web Docs: <a href=\"https://developer.mozilla.org/en-US/docs/Web/API/IndexedDB_API/Using_IndexedDB\" target=\"_blank\" rel=\"noopener\">Using IndexedDB</a> -- 完整 IndexedDB API 指南</li>\n<li>MDN Web Docs: <a href=\"https://developer.mozilla.org/en-US/docs/Web/API/Window/localStorage\" target=\"_blank\" rel=\"noopener\">Window.localStorage</a> -- localStorage API 參考</li>\n<li>MDN Web Docs: <a href=\"https://developer.mozilla.org/en-US/docs/Web/API/Storage_API/Storage_quotas_and_eviction_criteria\" target=\"_blank\" rel=\"noopener\">Storage quotas and eviction criteria</a> -- 儲存配額與驅逐策略</li>\n<li>Game Programming Patterns by Robert Nystrom -- 遊戲設計模式經典參考</li>\n<li>daily-digest-prompt 專案遊戲（輪迴塔、Pong、Breakout、念珠冥想）-- 實際應用場景</li>\n</ul>\n<hr>\n<p><em>研究日期：2026-02-19</em>\n<em>適用範圍：HTML5/JavaScript Canvas 遊戲開發</em>\n<em>相關知識庫筆記：遊戲狀態機 FSM、Canvas 粒子系統/物件池、ECS 架構、Game Loop 模式</em></p>\n","headings":[{"level":2,"text":"技術概述","slug":"技術概述"},{"level":2,"text":"一、儲存引擎比較與選型","slug":"一-儲存引擎比較與選型"},{"level":3,"text":"1.1 三大客戶端儲存方案","slug":"1-1-三大客戶端儲存方案"},{"level":3,"text":"1.2 選型決策樹","slug":"1-2-選型決策樹"},{"level":3,"text":"1.3 混合策略（推薦）","slug":"1-3-混合策略-推薦"},{"level":2,"text":"二、遊戲狀態序列化設計","slug":"二-遊戲狀態序列化設計"},{"level":3,"text":"2.1 存檔資料結構設計","slug":"2-1-存檔資料結構設計"},{"level":3,"text":"2.2 序列化與反序列化","slug":"2-2-序列化與反序列化"},{"level":2,"text":"三、自動存檔策略","slug":"三-自動存檔策略"},{"level":3,"text":"3.1 觸發時機設計","slug":"3-1-觸發時機設計"},{"level":3,"text":"3.2 自動存檔實作","slug":"3-2-自動存檔實作"},{"level":2,"text":"四、存檔版本遷移","slug":"四-存檔版本遷移"},{"level":2,"text":"五、資料完整性與防竄改","slug":"五-資料完整性與防竄改"},{"level":3,"text":"5.1 校驗和驗證","slug":"5-1-校驗和驗證"},{"level":3,"text":"5.2 備份與恢復","slug":"5-2-備份與恢復"},{"level":2,"text":"六、雲端同步設計","slug":"六-雲端同步設計"},{"level":3,"text":"6.1 同步架構","slug":"6-1-同步架構"},{"level":3,"text":"6.2 衝突解決策略","slug":"6-2-衝突解決策略"},{"level":3,"text":"6.3 離線優先同步模式","slug":"6-3-離線優先同步模式"},{"level":2,"text":"七、效能最佳化","slug":"七-效能最佳化"},{"level":3,"text":"7.1 差分存檔（Delta Save）","slug":"7-1-差分存檔-delta-save"},{"level":3,"text":"7.2 壓縮存檔","slug":"7-2-壓縮存檔"},{"level":3,"text":"7.3 避免遊戲迴圈中的同步 I/O","slug":"7-3-避免遊戲迴圈中的同步-i-o"},{"level":2,"text":"八、儲存配額與容錯","slug":"八-儲存配額與容錯"},{"level":3,"text":"8.1 配額管理","slug":"8-1-配額管理"},{"level":3,"text":"8.2 驅逐策略與防護","slug":"8-2-驅逐策略與防護"},{"level":2,"text":"九、存檔槽管理 UI 設計","slug":"九-存檔槽管理-ui-設計"},{"level":3,"text":"9.1 存檔槽資訊顯示","slug":"9-1-存檔槽資訊顯示"},{"level":3,"text":"9.2 操作流程","slug":"9-2-操作流程"},{"level":2,"text":"十、應用到 daily-digest-prompt 專案遊戲","slug":"十-應用到-daily-digest-prompt-專案遊戲"},{"level":3,"text":"直接適用的模式","slug":"直接適用的模式"},{"level":3,"text":"統一存檔介面","slug":"統一存檔介面"},{"level":2,"text":"參考來源","slug":"參考來源"}],"prev":{"slug":"pac-man-html5-canvas-ghost-99a5eeeb","title":"Pac-Man HTML5 Canvas 遊戲開發心得：Ghost AI、粒子系統與 8-bit 音效實作"},"next":{"slug":"v2-0-roguelike-b4652f5c","title":"輪迴塔 v2.0 品質優化心得：留存率導向的 Roguelike 設計模式"}}