{"id":"5be477b3-a205-452d-a84d-8935a5ca1e64","title":"Podcast 腳本：Hono 超輕量 Web 框架","slug":"podcast-腳本hono-超輕量-web-框架-5be477b3","category":"其他","categorySlug":"other","tags":["Podcast製作","對話腳本","雙主持人","hono-edge-framework"],"updatedAt":"2026-03-09","excerpt":"Podcast 腳本：Hono 超輕量 Web 框架 生成時間：20260309_130712 | 輸出：D:\\Source\\dailydigestprompt\\output\\podcasts\\Hono超輕量Web框架_2026030913","readingMin":4,"isNew":false,"html":"","headings":[],"prev":{"slug":"markdown-指令編輯與總結-skill-完整指南m-f1e69b41","title":"Markdown 指令、編輯與總結 Skill 完整指南（mechanism 階段）"},"next":{"slug":"gunjs-效能優化與分布式系統最佳實踐----基準測試-5efa48de","title":"Gun.js 效能優化與分布式系統最佳實踐 -- 基準測試、替代方案比較與生產環境容錯策略"}}