{"id":"20923901-3580-4d6e-ab90-e3fd36a2d740","title":"智慧治理 — AI 公文自動分類與陳情案件智能分流的優化策略：從 Portland 到台灣地方政府的落地指標（optimization，2026）","slug":"智慧治理-ai-公文自動分類與陳情案件智能分流的優化策略-20923901","category":"AI技術","categorySlug":"ai","tags":["AI","智慧城市","智慧治理","smart-city"],"updatedAt":"2026-04-07","excerpt":"智慧治理 — AI 公文自動分類與陳情案件智能分流的優化策略：從 Portland 到台灣地方政府的落地指標（optimization，2026） 本文為 aismartgovernance 系列第 optimization 階段，承接既有","readingMin":5,"isNew":false,"html":"","headings":[],"prev":{"slug":"sglangsgl-projectsglanggith-b99547eb","title":"SGLang（sgl-project/sglang）GitHub 熱門 AI 開源專案研究"},"next":{"slug":"harness-engineering-fitness-fu-196db9bc","title":"Harness Engineering Fitness Function 驅動的元件效能量化與自動調優策略 — 從架構適應度到 Meta-Harness 端對端優化的工程實踐"}}