{"id":"8a47e587-8d6e-42ce-bd69-f775a5d88386","title":"系統 Log 審查報告（2026-02-16）","slug":"系統-log-審查報告2026-02-16-8a47e587","category":"其他","categorySlug":"other","tags":["系統維護","Log審查","自動化"],"updatedAt":"2026-02-15","excerpt":"系統 Log 審查報告 審查日期：20260216 審查範圍：schedulerstate.json 近 90 筆記錄 + 結構化 JSONL 日誌 + 最近 10 個 log 檔案 整體健康度 狀態：🟢 健康 今日概況（2/16） 結構化","readingMin":1,"isNew":false,"html":"<h1 id=\"系統-log-審查報告\">系統 Log 審查報告</h1>\n<p><strong>審查日期</strong>：2026-02-16\n<strong>審查範圍</strong>：scheduler-state.json 近 90 筆記錄 + 結構化 JSONL 日誌 + 最近 10 個 log 檔案</p>\n<h2 id=\"整體健康度\">整體健康度</h2>\n<p><strong>狀態：🟢 健康</strong></p>\n<h3 id=\"今日概況-2-16\">今日概況（2/16）</h3>\n<ul>\n<li>結構化日誌：770 次工具呼叫</li>\n<li>攔截事件：0</li>\n<li>錯誤事件：0</li>\n<li>API 呼叫：126 次</li>\n<li>快取讀取：8 次</li>\n<li>Skill 讀取：10 次</li>\n</ul>\n<h3 id=\"執行記錄摘要\">執行記錄摘要</h3>\n<ul>\n<li>todoist 單一模式（04:00）：3/3 任務成功 + 1 自動任務（Skill 審查），耗時 2054s</li>\n<li>todoist-team（03:30）：3/3 任務成功（知識庫網站部署 + 遊戲優化 + 遊戲網站部署），耗時 1068s</li>\n<li>todoist-team（04:30）：skill_audit 自動任務成功，耗時 674s</li>\n</ul>\n<h3 id=\"近期趨勢-2-15-2-16\">近期趨勢（2/15-2/16）</h3>\n<ul>\n<li><strong>成功率</strong>：100%（修正 Phase 1 timeout 後，近 40+ 筆執行全部成功）</li>\n<li><strong>平均耗時</strong>：todoist-team ~400-700s、todoist 單一 ~300-900s</li>\n<li><strong>自動任務輪轉</strong>：正常運作（涵蓋 skill_audit, tech_research, unsloth, ai_sysdev, jiaoguangzong, fahua, creative_game 等）</li>\n</ul>\n<h2 id=\"歷史問題追蹤\">歷史問題追蹤</h2>\n<h3 id=\"已修復-todoist-team-phase-1-連續-timeout-2-15\">已修復：todoist-team Phase 1 連續 TIMEOUT（2/15）</h3>\n<ul>\n<li><strong>問題</strong>：2/15 凌晨 02:00-07:00 連續 12 次 Phase 1 TIMEOUT</li>\n<li><strong>根因</strong>：timeout 設定 180s 過短</li>\n<li><strong>修復</strong>：已調整為 300s</li>\n<li><strong>驗證</strong>：修復後所有 Phase 1 穩定完成</li>\n</ul>\n<h3 id=\"已修復-daily-digest-team-hackernews-gmail-t\">已修復：daily-digest-team hackernews/gmail TIMEOUT（2/15）</h3>\n<ul>\n<li>Phase1 timeout 180s → 調整為 300s</li>\n<li>後續執行全部正常</li>\n</ul>\n<h2 id=\"結論\">結論</h2>\n<p>系統運行穩定，無需修復。所有歷史問題已在前次 Log 審查中修正並驗證通過。自動任務輪轉機制、品質閘門、知識庫匯入等功能正常運作。</p>\n","headings":[{"level":2,"text":"整體健康度","slug":"整體健康度"},{"level":3,"text":"今日概況（2/16）","slug":"今日概況-2-16"},{"level":3,"text":"執行記錄摘要","slug":"執行記錄摘要"},{"level":3,"text":"近期趨勢（2/15-2/16）","slug":"近期趨勢-2-15-2-16"},{"level":2,"text":"歷史問題追蹤","slug":"歷史問題追蹤"},{"level":3,"text":"已修復：todoist-team Phase 1 連續 TIMEOUT（2/15）","slug":"已修復-todoist-team-phase-1-連續-timeout-2-15"},{"level":3,"text":"已修復：daily-digest-team hackernews/gmail TIMEOUT（2/15）","slug":"已修復-daily-digest-team-hackernews-gmail-t"},{"level":2,"text":"結論","slug":"結論"}],"prev":{"slug":"skill-品質審查報告-2026-02-17system-54ef1807","title":"Skill 品質審查報告 2026-02-17（system-insight + kb-curator 深度審查）"},"next":{"slug":"skill-品質審查報告-2026-02-16ntfy-n-01b8c7ad","title":"Skill 品質審查報告 2026-02-16（ntfy-notify + task-manager + 全局一致性）"}}